LICENSE
MANIFEST.in
README.md
pyproject.toml
setup.cfg
setup.py
crawlertool/__init__.py
crawlertool/basic.py
crawlertool/request.py
crawlertool.egg-info/PKG-INFO
crawlertool.egg-info/SOURCES.txt
crawlertool.egg-info/dependency_links.txt
crawlertool.egg-info/requires.txt
crawlertool.egg-info/top_level.txt
crawlertool/_abc/__init__.py
crawlertool/_abc/base_spider.py
crawlertool/_abc/loop_spider.py
crawlertool/_abc/single_spider.py
crawlertool/db/__init__.py
crawlertool/db/_mysql.py
crawlertool/extract/__init__.py
crawlertool/extract/string.py
crawlertool/io/__init__.py
crawlertool/io/csv.py
crawlertool/io/excel.py
crawlertool/io/file.py
crawlertool/io/json.py
crawlertool/io/mysql.py
crawlertool/static/__init__.py
crawlertool/static/user_agent.py