Metadata-Version: 2.1
Name: crawlertool
Version: 0.1.23
Summary: Tools for Spiders
Home-page: https://github.com/ChangxingJiang/CrawlerTool
Author: ChangXing
Author-email: 1278729001@qq.com
License: UNKNOWN
Platform: UNKNOWN
Classifier: Development Status :: 3 - Alpha
Classifier: License :: OSI Approved :: MIT License
Classifier: Programming Language :: Python :: 3.8
Classifier: Programming Language :: Python
